explorator/__init__.py
explorator/functions.py
explorator/general_info.py
explorator/total_review.py
explorator-0.0.15.dist-info/METADATA
explorator-0.0.15.dist-info/WHEEL
explorator-0.0.15.dist-info/top_level.txt
explorator-0.0.15.dist-info/RECORD
