Metadata-Version: 2.1
Name: explorator
Version: 0.0.15
Summary: Package to quickly explore data in pandas dataframe
Home-page: UNKNOWN
Author: Boris Zakhir
Author-email: bz@omnichannel.ru
License: UNKNOWN
Keywords: pandas,exploratory
Platform: UNKNOWN
